Polymarket/__init__.py
Polymarket/polymarket.py
polymarket_py-0.1.0.dist-info/METADATA
polymarket_py-0.1.0.dist-info/WHEEL
polymarket_py-0.1.0.dist-info/top_level.txt
polymarket_py-0.1.0.dist-info/RECORD
