Metadata-Version: 2.1
Name: polymarket-py
Version: 0.1.0
Summary: A package to export historical odds for an outcome of a market on Polymarket
Home-page: https://github.com/MattMaximo/polymarket-py
Author: Matt Maximo
Author-email: matt@pioneerdigital.org
Keywords: polymarket,crypto,data,api,exporter,market,odds
Classifier: Programming Language :: Python :: 3
Classifier: License :: OSI Approved :: MIT License
Classifier: Operating System :: OS Independent
Requires-Python: >=3.6
Requires-Dist: requests
Requires-Dist: pandas
Requires-Dist: pytz
